setup.py
doc/config/freetile.khotkeys
doc/config/freetile.scm
doc/config/freetilerc
freetile/__init__.py
freetile/__main__.py
freetile/auto.py
freetile/config.py
freetile/divide.py
freetile/main.py
freetile/monitor.py
freetile/nontree.py
freetile/test.py
freetile/tree.py
freetile/util_kdtree.py
freetile/windowlist.py
freetile/workarea.py
freetile.egg-info/PKG-INFO
freetile.egg-info/SOURCES.txt
freetile.egg-info/dependency_links.txt
freetile.egg-info/entry_points.txt
freetile.egg-info/requires.txt
freetile.egg-info/top_level.txt
freetile/helper/__init__.py
freetile/helper/helper_ewmh.py
freetile/helper/xcb.py
freetile/helper/xlib.py