Metadata-Version: 1.1
Name: freetile
Version: 0.1.3
Summary: freely tiling script for X
Home-page: http://github.com/rbn42/freetile
Author: rbn42
Author-email: bl100@students.waikato.ac.nz
License: MIT
Download-URL: https://github.com/rbn42/freetile/archive/v0.1.3.tar.gz
Keywords: window,tiling,xorg
Platform: UNKNOWN
Classifier: Development Status :: 2 - Pre-Alpha
Classifier: Environment :: X11 Applications
Classifier: Intended Audience :: End Users/Desktop
Classifier: License :: OSI Approved :: MIT License
Classifier: Programming Language :: Python :: 3
Classifier: Topic :: Desktop Environment :: Window Managers
